hatch_minify/__init__.py
hatch_minify/hooks.py
hatch_minify/plugin.py
hatch_minify-0.1.0.dist-info/METADATA
hatch_minify-0.1.0.dist-info/WHEEL
hatch_minify-0.1.0.dist-info/entry_points.txt
hatch_minify-0.1.0.dist-info/licenses/LICENSE
hatch_minify-0.1.0.dist-info/RECORD
