Metadata-Version: 2.3
Name: hatch-minify
Version: 0.1.0
Summary: A hatch build hook python minifier
Project-URL: Documentation, https://github.com/djcopley/hatch-minify#readme
Project-URL: Issues, https://github.com/djcopley/hatch-minify/issues
Project-URL: Source, https://github.com/djcopley/hatch-minify
Author-email: Daniel Copley <djcopley@proton.me>
License:                     GNU GENERAL PUBLIC LICENSE
Classifier: Development Status :: 3 - Alpha
Classifier: Programming Language :: Python
Classifier: Programming Language :: Python :: 3.8
Classifier: Programming Language :: Python :: 3.9
Classifier: Programming Language :: Python :: 3.10
Classifier: Programming Language :: Python :: 3.11
Classifier: Programming Language :: Python :: 3.12
Classifier: Programming Language :: Python :: Implementation :: CPython
Classifier: Programming Language :: Python :: Implementation :: PyPy
Requires-Python: >=3.8
Requires-Dist: hatchling
Requires-Dist: python-minifier
